traffic_controller.v
module traffic_controller ( 
    input [3:0] Traffic,
    input clk, rst, 
    output reg [3:0]Red, Green, Yellow
    );  

    parameter [2:0] s_idle = 3'b000,
        s_13gg = 3'b001,
        s_13yy = 3'b010,
        s_24gg = 3'b011,
        s_24yy = 3'b100;
        reg [2:0] ps,ns;
        reg [16:0]max_timer; 
        reg done;
        
    // Now lets write the state transition diagram 
    always @(*) begin
        case (ps)
            s_idle: if (~|Traffic) begin
                ns = s_idle;
            end else begin
                if (Traffic[0] || Traffic[2]) begin
                    ns = s_13gg;
                end else begin
                    if (Traffic[1] || Traffic[3]) begin
                        ns = s_24gg;
                    end else begin
                        ns = s_idle;
                    end
                end
            end
            s_13gg: if (done) begin
                ns = s_13yy;
            end else begin
                ns = s_13gg;
            end
            s_13yy: if (done) begin
                ns = s_idle;
            end else begin
                ns = s_13yy;
            end
            s_24gg: if (done) begin
                ns =s_24yy;
            end else begin
                ns = s_24gg;
            end
            s_24yy: if (done) begin
                ns = s_idle;
            end else begin
                ns = s_24yy;
            end
            default: ns = s_idle;
        endcase
    end
    // Now we write the state memory 

    always @(posedge clk or posedge rst ) begin
        if (rst) begin
            ps <= s_idle;
        end else begin
            ps<=ns;
        end
    end
    // Memory of the state done

    //Now comes the counter, the main and the ped counter for that we declare the max times first 
    parameter GREEN_TIME  = 16'd55;
    parameter YELLOW_TIME = 16'd10;



    // Main timer block

    always @(posedge clk or posedge rst) begin
        if (rst) begin
            max_timer <= 16'd0;
            done <= 0;
        end else begin
            case (ps)
                s_13gg: begin
                    if (max_timer == 0) begin
                        max_timer <= GREEN_TIME;
                    end else begin
                        if (max_timer > 0) begin
                            max_timer <= max_timer - 1;
                            done <= (max_timer-1 ==0);
                        end else begin
                            done <= 0;
                        end
                    end
                end
                s_13yy: begin
                    if (max_timer == 0) begin
                        max_timer <= YELLOW_TIME;
                    end else begin
                        if (max_timer > 0) begin
                            max_timer <= max_timer - 1;
                            done <= (max_timer-1 == 0);
                        end else begin
                            done <= 0;
                        end
                    end
                end
                s_24gg: begin
                    if (max_timer == 0) begin
                        max_timer <= GREEN_TIME;
                    end else begin
                        if (max_timer > 0) begin
                            max_timer <= max_timer - 1;
                            done <= (max_timer-1 ==0);
                        end else begin
                            done <= 0;
                        end
                    end
                end
                s_24yy: begin
                    if (max_timer == 0) begin
                        max_timer <= YELLOW_TIME;
                    end else begin
                        if (max_timer > 0) begin
                            max_timer <= max_timer - 1;
                            done <= (max_timer-1 ==0);
                        end else begin
                            done <= 0;
                        end
                    end
                end
                default : done <= 0; 
            endcase
        end
    end

    // Now comes the output logic
    always @(*) begin
        // Default values for all outputs
         Red = 4'b0000;
         Green = 4'b0000;
         Yellow = 4'b0000;

        case (ps)
            s_idle: begin
                Red = 4'b1111;
                Green = 4'b0000;
                Yellow = 4'b0000;
            end

            s_13gg: begin
                Red  = 4'b1010;
                Green = 4'b0101;
            end

            s_13yy: begin
                Red = 4'b1010;
                Yellow = 4'b0101;
                Green = 4'b0000;
            end

            s_24gg: begin
                Red  = 4'b0101;
                Green = 4'b1010;
            end

            s_24yy: begin
                Red = 4'b0101;
                Yellow = 4'b1010;
                Green = 4'b0000;
            end

            default: begin
                Red = 4'b1111; 
            end
        endcase
    end
endmodule

traffic_controller_tb.v
`timescale 1ns / 1ps
`include "traffic_controller.v"
module traffic_controller_tb;

    // Inputs
    reg [3:0]T;
    reg clk, rst;

    // Outputs
    wire [3:0] r, g, y;


    // Instantiate the Unit Under Test (UUT)
    traffic_controller uut (.Traffic(T), 
    .clk(clk), .rst(rst), .Red(r), .Green(g), .Yellow(y));

    // Clock generation: 10 ns period
    initial begin
        clk = 0;
        forever #5 clk = ~clk;
    end

    initial begin
        $dumpfile("traffic_controller_tb.vcd");
        $dumpvars(0, traffic_controller_tb);

        // Initialize inputs
        T = 4'b000;
        rst = 1;

        // Hold reset for a few clock cycles
        #20;
        rst = 0;

        // --- Test case 1: Traffic on lane 1 ---
        T = 4'b1000;
        // Wait enough time for full traffic to complete
        #600;
                // --- Test case 1: Traffic on lane 3  ---
        T = 4'b0100;
        // Wait enough time for full traffic a
        #600;

        // --- Test case 2: Traffic on lane 2 & 4 and pedestrian on ped_24 ---
        T = 4'b1010;
        // Wait enough time for full traffic a
        #600;

        // --- Test case 3: No traffic or pedestrians (idle state) ---
        T = 4'b0000;

        #100;

        // Finish simulation
        $finish;
    end

    // Simple monitoring to print relevant signals at every clock positive edge
    always @(posedge clk) begin
        $display("Time: %0t ns | rst=%b | T=%b%b%b%b | R=%b%b%b%b G=%b%b%b%b Y=%b%b%b%b | State=%d Timer=%d Done=%b",
            $time, rst,
            T[3], T[2], T[1], T[0],     // Traffic bits
            r[3], r[2], r[1], r[0],     // Red lights
            g[3], g[2], g[1], g[0],     // Green lights  
            y[3], y[2], y[1], y[0],     // Yellow lights
            uut.ps,                     // Current state
            uut.max_timer,              // Timer value
            uut.done                    // Done signal
        );
    end

endmodule

traffic_controller_tb.vcd
$date
	Thu Jul 31 00:58:42 2025
$end
$version
	Icarus Verilog
$end
$timescale
	1ps
$end
$scope module traffic_controller_tb $end
$var wire 4 ! g [3:0] $end
$var wire 4 " r [3:0] $end
$var wire 4 # y [3:0] $end
$var reg 4 $ T [3:0] $end
$var reg 1 % clk $end
$var reg 1 & rst $end
$scope module uut $end
$var wire 4 ' Traffic [3:0] $end
$var wire 1 ( clk $end
$var wire 1 ) rst $end
$var reg 4 * Green [3:0] $end
$var reg 4 + Red [3:0] $end
$var reg 4 , Yellow [3:0] $end
$var reg 1 - done $end
$var reg 17 . max_timer [16:0] $end
$var reg 3 / ns [2:0] $end
$var reg 3 0 ps [2:0] $end
$upscope $end
$upscope $end
$enddefinitions $end
#0
$dumpvars
b0 0
b0 /
b0 .
0-
b0 ,
b1111 +
b0 *
1)
0(
b0 '
1&
0%
b0 $
b0 #
b1111 "
b0 !
$end
#5000
1%
1(
#10000
0%
0(
#15000
1%
1(
#20000
b11 /
0%
0(
b1000 $
b1000 '
0&
0)
#25000
b1010 *
b1010 !
b101 +
b101 "
b11 0
1%
1(
#30000
0%
0(
#35000
b110111 .
1%
1(
#40000
0%
0(
#45000
b110110 .
1%
1(
#50000
0%
0(
#55000
b110101 .
1%
1(
#60000
0%
0(
#65000
b110100 .
1%
1(
#70000
0%
0(
#75000
b110011 .
1%
1(
#80000
0%
0(
#85000
b110010 .
1%
1(
#90000
0%
0(
#95000
b110001 .
1%
1(
#100000
0%
0(
#105000
b110000 .
1%
1(
#110000
0%
0(
#115000
b101111 .
1%
1(
#120000
0%
0(
#125000
b101110 .
1%
1(
#130000
0%
0(
#135000
b101101 .
1%
1(
#140000
0%
0(
#145000
b101100 .
1%
1(
#150000
0%
0(
#155000
b101011 .
1%
1(
#160000
0%
0(
#165000
b101010 .
1%
1(
#170000
0%
0(
#175000
b101001 .
1%
1(
#180000
0%
0(
#185000
b101000 .
1%
1(
#190000
0%
0(
#195000
b100111 .
1%
1(
#200000
0%
0(
#205000
b100110 .
1%
1(
#210000
0%
0(
#215000
b100101 .
1%
1(
#220000
0%
0(
#225000
b100100 .
1%
1(
#230000
0%
0(
#235000
b100011 .
1%
1(
#240000
0%
0(
#245000
b100010 .
1%
1(
#250000
0%
0(
#255000
b100001 .
1%
1(
#260000
0%
0(
#265000
b100000 .
1%
1(
#270000
0%
0(
#275000
b11111 .
1%
1(
#280000
0%
0(
#285000
b11110 .
1%
1(
#290000
0%
0(
#295000
b11101 .
1%
1(
#300000
0%
0(
#305000
b11100 .
1%
1(
#310000
0%
0(
#315000
b11011 .
1%
1(
#320000
0%
0(
#325000
b11010 .
1%
1(
#330000
0%
0(
#335000
b11001 .
1%
1(
#340000
0%
0(
#345000
b11000 .
1%
1(
#350000
0%
0(
#355000
b10111 .
1%
1(
#360000
0%
0(
#365000
b10110 .
1%
1(
#370000
0%
0(
#375000
b10101 .
1%
1(
#380000
0%
0(
#385000
b10100 .
1%
1(
#390000
0%
0(
#395000
b10011 .
1%
1(
#400000
0%
0(
#405000
b10010 .
1%
1(
#410000
0%
0(
#415000
b10001 .
1%
1(
#420000
0%
0(
#425000
b10000 .
1%
1(
#430000
0%
0(
#435000
b1111 .
1%
1(
#440000
0%
0(
#445000
b1110 .
1%
1(
#450000
0%
0(
#455000
b1101 .
1%
1(
#460000
0%
0(
#465000
b1100 .
1%
1(
#470000
0%
0(
#475000
b1011 .
1%
1(
#480000
0%
0(
#485000
b1010 .
1%
1(
#490000
0%
0(
#495000
b1001 .
1%
1(
#500000
0%
0(
#505000
b1000 .
1%
1(
#510000
0%
0(
#515000
b111 .
1%
1(
#520000
0%
0(
#525000
b110 .
1%
1(
#530000
0%
0(
#535000
b101 .
1%
1(
#540000
0%
0(
#545000
b100 .
1%
1(
#550000
0%
0(
#555000
b11 .
1%
1(
#560000
0%
0(
#565000
b10 .
1%
1(
#570000
0%
0(
#575000
b1 .
1%
1(
#580000
0%
0(
#585000
b100 /
1-
b0 .
1%
1(
#590000
0%
0(
#595000
b1010 ,
b1010 #
b0 *
b0 !
b101 +
b101 "
b0 /
b100 0
b110111 .
1%
1(
#600000
0%
0(
#605000
b0 ,
b0 #
b1111 +
b1111 "
b11 /
0-
b110110 .
b0 0
1%
1(
#610000
0%
0(
#615000
b1010 *
b1010 !
b101 +
b101 "
b11 0
1%
1(
#620000
0%
0(
b100 $
b100 '
#625000
b110101 .
1%
1(
#630000
0%
0(
#635000
b110100 .
1%
1(
#640000
0%
0(
#645000
b110011 .
1%
1(
#650000
0%
0(
#655000
b110010 .
1%
1(
#660000
0%
0(
#665000
b110001 .
1%
1(
#670000
0%
0(
#675000
b110000 .
1%
1(
#680000
0%
0(
#685000
b101111 .
1%
1(
#690000
0%
0(
#695000
b101110 .
1%
1(
#700000
0%
0(
#705000
b101101 .
1%
1(
#710000
0%
0(
#715000
b101100 .
1%
1(
#720000
0%
0(
#725000
b101011 .
1%
1(
#730000
0%
0(
#735000
b101010 .
1%
1(
#740000
0%
0(
#745000
b101001 .
1%
1(
#750000
0%
0(
#755000
b101000 .
1%
1(
#760000
0%
0(
#765000
b100111 .
1%
1(
#770000
0%
0(
#775000
b100110 .
1%
1(
#780000
0%
0(
#785000
b100101 .
1%
1(
#790000
0%
0(
#795000
b100100 .
1%
1(
#800000
0%
0(
#805000
b100011 .
1%
1(
#810000
0%
0(
#815000
b100010 .
1%
1(
#820000
0%
0(
#825000
b100001 .
1%
1(
#830000
0%
0(
#835000
b100000 .
1%
1(
#840000
0%
0(
#845000
b11111 .
1%
1(
#850000
0%
0(
#855000
b11110 .
1%
1(
#860000
0%
0(
#865000
b11101 .
1%
1(
#870000
0%
0(
#875000
b11100 .
1%
1(
#880000
0%
0(
#885000
b11011 .
1%
1(
#890000
0%
0(
#895000
b11010 .
1%
1(
#900000
0%
0(
#905000
b11001 .
1%
1(
#910000
0%
0(
#915000
b11000 .
1%
1(
#920000
0%
0(
#925000
b10111 .
1%
1(
#930000
0%
0(
#935000
b10110 .
1%
1(
#940000
0%
0(
#945000
b10101 .
1%
1(
#950000
0%
0(
#955000
b10100 .
1%
1(
#960000
0%
0(
#965000
b10011 .
1%
1(
#970000
0%
0(
#975000
b10010 .
1%
1(
#980000
0%
0(
#985000
b10001 .
1%
1(
#990000
0%
0(
#995000
b10000 .
1%
1(
#1000000
0%
0(
#1005000
b1111 .
1%
1(
#1010000
0%
0(
#1015000
b1110 .
1%
1(
#1020000
0%
0(
#1025000
b1101 .
1%
1(
#1030000
0%
0(
#1035000
b1100 .
1%
1(
#1040000
0%
0(
#1045000
b1011 .
1%
1(
#1050000
0%
0(
#1055000
b1010 .
1%
1(
#1060000
0%
0(
#1065000
b1001 .
1%
1(
#1070000
0%
0(
#1075000
b1000 .
1%
1(
#1080000
0%
0(
#1085000
b111 .
1%
1(
#1090000
0%
0(
#1095000
b110 .
1%
1(
#1100000
0%
0(
#1105000
b101 .
1%
1(
#1110000
0%
0(
#1115000
b100 .
1%
1(
#1120000
0%
0(
#1125000
b11 .
1%
1(
#1130000
0%
0(
#1135000
b10 .
1%
1(
#1140000
0%
0(
#1145000
b1 .
1%
1(
#1150000
0%
0(
#1155000
b100 /
1-
b0 .
1%
1(
#1160000
0%
0(
#1165000
b1010 ,
b1010 #
b0 *
b0 !
b101 +
b101 "
b0 /
b110111 .
b100 0
1%
1(
#1170000
0%
0(
#1175000
b0 ,
b0 #
b1111 +
b1111 "
b1 /
b0 0
0-
b110110 .
1%
1(
#1180000
0%
0(
#1185000
b101 *
b101 !
b1010 +
b1010 "
b1 0
1%
1(
#1190000
0%
0(
#1195000
b110101 .
1%
1(
#1200000
0%
0(
#1205000
b110100 .
1%
1(
#1210000
0%
0(
#1215000
b110011 .
1%
1(
#1220000
0%
0(
b1010 $
b1010 '
#1225000
b110010 .
1%
1(
#1230000
0%
0(
#1235000
b110001 .
1%
1(
#1240000
0%
0(
#1245000
b110000 .
1%
1(
#1250000
0%
0(
#1255000
b101111 .
1%
1(
#1260000
0%
0(
#1265000
b101110 .
1%
1(
#1270000
0%
0(
#1275000
b101101 .
1%
1(
#1280000
0%
0(
#1285000
b101100 .
1%
1(
#1290000
0%
0(
#1295000
b101011 .
1%
1(
#1300000
0%
0(
#1305000
b101010 .
1%
1(
#1310000
0%
0(
#1315000
b101001 .
1%
1(
#1320000
0%
0(
#1325000
b101000 .
1%
1(
#1330000
0%
0(
#1335000
b100111 .
1%
1(
#1340000
0%
0(
#1345000
b100110 .
1%
1(
#1350000
0%
0(
#1355000
b100101 .
1%
1(
#1360000
0%
0(
#1365000
b100100 .
1%
1(
#1370000
0%
0(
#1375000
b100011 .
1%
1(
#1380000
0%
0(
#1385000
b100010 .
1%
1(
#1390000
0%
0(
#1395000
b100001 .
1%
1(
#1400000
0%
0(
#1405000
b100000 .
1%
1(
#1410000
0%
0(
#1415000
b11111 .
1%
1(
#1420000
0%
0(
#1425000
b11110 .
1%
1(
#1430000
0%
0(
#1435000
b11101 .
1%
1(
#1440000
0%
0(
#1445000
b11100 .
1%
1(
#1450000
0%
0(
#1455000
b11011 .
1%
1(
#1460000
0%
0(
#1465000
b11010 .
1%
1(
#1470000
0%
0(
#1475000
b11001 .
1%
1(
#1480000
0%
0(
#1485000
b11000 .
1%
1(
#1490000
0%
0(
#1495000
b10111 .
1%
1(
#1500000
0%
0(
#1505000
b10110 .
1%
1(
#1510000
0%
0(
#1515000
b10101 .
1%
1(
#1520000
0%
0(
#1525000
b10100 .
1%
1(
#1530000
0%
0(
#1535000
b10011 .
1%
1(
#1540000
0%
0(
#1545000
b10010 .
1%
1(
#1550000
0%
0(
#1555000
b10001 .
1%
1(
#1560000
0%
0(
#1565000
b10000 .
1%
1(
#1570000
0%
0(
#1575000
b1111 .
1%
1(
#1580000
0%
0(
#1585000
b1110 .
1%
1(
#1590000
0%
0(
#1595000
b1101 .
1%
1(
#1600000
0%
0(
#1605000
b1100 .
1%
1(
#1610000
0%
0(
#1615000
b1011 .
1%
1(
#1620000
0%
0(
#1625000
b1010 .
1%
1(
#1630000
0%
0(
#1635000
b1001 .
1%
1(
#1640000
0%
0(
#1645000
b1000 .
1%
1(
#1650000
0%
0(
#1655000
b111 .
1%
1(
#1660000
0%
0(
#1665000
b110 .
1%
1(
#1670000
0%
0(
#1675000
b101 .
1%
1(
#1680000
0%
0(
#1685000
b100 .
1%
1(
#1690000
0%
0(
#1695000
b11 .
1%
1(
#1700000
0%
0(
#1705000
b10 .
1%
1(
#1710000
0%
0(
#1715000
b1 .
1%
1(
#1720000
0%
0(
#1725000
b10 /
1-
b0 .
1%
1(
#1730000
0%
0(
#1735000
b101 ,
b101 #
b0 *
b0 !
b1010 +
b1010 "
b0 /
b10 0
b110111 .
1%
1(
#1740000
0%
0(
#1745000
b0 ,
b0 #
b1111 +
b1111 "
b11 /
0-
b110110 .
b0 0
1%
1(
#1750000
0%
0(
#1755000
b1010 *
b1010 !
b101 +
b101 "
b11 0
1%
1(
#1760000
0%
0(
#1765000
b110101 .
1%
1(
#1770000
0%
0(
#1775000
b110100 .
1%
1(
#1780000
0%
0(
#1785000
b110011 .
1%
1(
#1790000
0%
0(
#1795000
b110010 .
1%
1(
#1800000
0%
0(
#1805000
b110001 .
1%
1(
#1810000
0%
0(
#1815000
b110000 .
1%
1(
#1820000
0%
0(
b0 $
b0 '
#1825000
b101111 .
1%
1(
#1830000
0%
0(
#1835000
b101110 .
1%
1(
#1840000
0%
0(
#1845000
b101101 .
1%
1(
#1850000
0%
0(
#1855000
b101100 .
1%
1(
#1860000
0%
0(
#1865000
b101011 .
1%
1(
#1870000
0%
0(
#1875000
b101010 .
1%
1(
#1880000
0%
0(
#1885000
b101001 .
1%
1(
#1890000
0%
0(
#1895000
b101000 .
1%
1(
#1900000
0%
0(
#1905000
b100111 .
1%
1(
#1910000
0%
0(
#1915000
b100110 .
1%
1(
